autocompl/__init__.py
autocompl/compl.py
autocompl/prefix_tree.py
autocompl/words.py
pyauto_compl-0.1.dist-info/LICENSE
pyauto_compl-0.1.dist-info/METADATA
pyauto_compl-0.1.dist-info/WHEEL
pyauto_compl-0.1.dist-info/top_level.txt
pyauto_compl-0.1.dist-info/RECORD
