Metadata-Version: 2.1
Name: pyauto-compl
Version: 0.1
Summary: Library for auto complete in Python. It comes with set of standard english words for quick start.
Home-page: https://github.com/farkon00/pyauto-compl
Author: farkon00
Author-email: sammer2016sammer@gmail.com
License: MIT
Classifier: Programming Language :: Python :: 3
Classifier: License :: OSI Approved :: MIT License
Classifier: Operating System :: OS Independent
Requires-Python: >=3.6
License-File: LICENSE
